skill_launcher/LICENSE.md
skill_launcher/README.md
skill_launcher/__init__.py
skill_launcher/skill.json
skill_launcher/version.py
skill_launcher/locale/en-us/dialog/dot.dialog
skill_launcher/locale/en-us/dialog/launch_program.dialog
skill_launcher/locale/en-us/dialog/launch_website.dialog
skill_launcher/locale/en-us/dialog/mobile_not_supported.dialog
skill_launcher/locale/en-us/dialog/not_supported.dialog
skill_launcher/locale/en-us/dialog/on.dialog
skill_launcher/locale/en-us/dialog/website_not_found.dialog
skill_launcher/locale/en-us/regex/website.rx
skill_launcher/locale/en-us/vocab/browse.voc
skill_launcher/locale/en-us/vocab/launch.voc
skill_launcher/locale/en-us/vocab/launch_program.intent
skill_launcher/neon_skill_launcher.egg-info/PKG-INFO
skill_launcher/neon_skill_launcher.egg-info/SOURCES.txt
skill_launcher/neon_skill_launcher.egg-info/dependency_links.txt
skill_launcher/neon_skill_launcher.egg-info/entry_points.txt
skill_launcher/neon_skill_launcher.egg-info/requires.txt
skill_launcher/neon_skill_launcher.egg-info/top_level.txt
skill_launcher/test/test_skill.py
neon_skill_launcher-1.1.0.dist-info/LICENSE.md
neon_skill_launcher-1.1.0.dist-info/METADATA
neon_skill_launcher-1.1.0.dist-info/WHEEL
neon_skill_launcher-1.1.0.dist-info/entry_points.txt
neon_skill_launcher-1.1.0.dist-info/top_level.txt
neon_skill_launcher-1.1.0.dist-info/RECORD
